GSForge/__init__.py
GSForge/_singledispatchmethod.py
GSForge/models/_AnnotatedGEM.py
GSForge/models/_GeneSet.py
GSForge/models/_GeneSetCollection.py
GSForge/models/_Interface.py
GSForge/models/__init__.py
GSForge/models/_utils.py
GSForge/operations/__init__.py
GSForge/operations/analytics.py
GSForge/operations/core.py
GSForge/operations/normalizations.py
GSForge/operations/prospectors.py
GSForge/plots/__init__.py
GSForge/plots/abstract_plot_models.py
GSForge/plots/annotations/__init__.py
GSForge/plots/annotations/_annotation_bars.py
GSForge/plots/collections/__init__.py
GSForge/plots/collections/_geneset_heatmap.py
GSForge/plots/collections/_upsetplot_interface.py
GSForge/plots/gem/__init__.py
GSForge/plots/gem/_gene_count_vs_time.py
GSForge/plots/gem/_gene_mass.py
GSForge/plots/gem/_gene_vs_counts_scatter.py
GSForge/plots/gem/_genewise_aggregate_scatter.py
GSForge/plots/gem/_grouped_gene_covariance.py
GSForge/plots/gem/_raster_gem.py
GSForge/plots/gem/_sampliewise_distributions.py
GSForge/plots/results/__init__.py
GSForge/plots/results/_lfc_vs_mean.py
GSForge/plots/results/_volcano.py
GSForge/utils/R_interface.py
GSForge/utils/__init__.py
GSForge/utils/_models.py
GSForge/utils/_operations.py
GSForge/utils/converters.py
GSForge/utils/enrichment.py
GSForge/utils/generate_gem.py
GSForge-1.0.2.dist-info/LICENSE.txt
GSForge-1.0.2.dist-info/METADATA
GSForge-1.0.2.dist-info/WHEEL
GSForge-1.0.2.dist-info/top_level.txt
GSForge-1.0.2.dist-info/RECORD
