Metadata-Version: 2.1
Name: GSForge
Version: 1.0.2
Summary: Feature (gene) selection package for gene expression data.
Home-page: https://systemsgenetics.github.io/GSForge/
Author: Tyler Biggs
Author-email: tyler.biggs@wsu.edu
License: LICENSE.txt
Platform: UNKNOWN
Requires-Python: >=3.6
License-File: LICENSE.txt
Requires-Dist: numpy (>=1.17.3)
Requires-Dist: pandas (>=1.3)
Requires-Dist: xarray (>=0.12.3)
Requires-Dist: param
Requires-Dist: Boruta
Requires-Dist: bokeh
Requires-Dist: click
Requires-Dist: datashader
Requires-Dist: h5py
Requires-Dist: holoviews
Requires-Dist: matplotlib
Requires-Dist: graphviz
Requires-Dist: methodtools
Requires-Dist: netcdf4
Requires-Dist: panel
Requires-Dist: scikit-learn
Requires-Dist: scipy
Requires-Dist: seaborn
Requires-Dist: statsmodels
Requires-Dist: umap-learn
Requires-Dist: pynndescent
Requires-Dist: selenium
Requires-Dist: upsetplot
Provides-Extra: r_support
Requires-Dist: rpy2 ; extra == 'r_support'
Provides-Extra: docs
Requires-Dist: sphinx ; extra == 'docs'
Requires-Dist: nbsphinx ; extra == 'docs'
Requires-Dist: selenium ; extra == 'docs'
Requires-Dist: sphinx-gallery ; extra == 'docs'
Requires-Dist: sphinx-rtd-theme ; extra == 'docs'
Requires-Dist: jupyterlab ; extra == 'docs'
Requires-Dist: recommonmark ; extra == 'docs'
Requires-Dist: myst-nb ; extra == 'docs'
